Metadata-Version: 2.1
Name: csv-zip-rsync
Version: 0.2.0
Summary: compress csv to zip and rsync to remote server
Home-page: https://github.com/fx-kirin/csv_zip_rsync
Author: fx-kirin
Author-email: fx.kirin@gmail.com
License: MIT
Classifier: Development Status :: 2 - Pre-Alpha
Classifier: License :: OSI Approved :: MIT License
Classifier: Programming Language :: Python
Classifier: Programming Language :: Python :: 2
Classifier: Programming Language :: Python :: 2.7
Classifier: Programming Language :: Python :: 3
Classifier: Programming Language :: Python :: 3.4
Classifier: Programming Language :: Python :: 3.5
Classifier: Programming Language :: Python :: 3.6
Classifier: Programming Language :: Python :: 3.7
License-File: LICENSE
